MANIFEST.in
README.txt
setup.py
Products/__init__.py
Products.rendezvous.egg-info/PKG-INFO
Products.rendezvous.egg-info/SOURCES.txt
Products.rendezvous.egg-info/dependency_links.txt
Products.rendezvous.egg-info/entry_points.txt
Products.rendezvous.egg-info/namespace_packages.txt
Products.rendezvous.egg-info/not-zip-safe
Products.rendezvous.egg-info/requires.txt
Products.rendezvous.egg-info/top_level.txt
Products/rendezvous/__init__.py
Products/rendezvous/config.py
Products/rendezvous/configure.zcml
Products/rendezvous/profiles.zcml
Products/rendezvous/refresh.txt
Products/rendezvous/setuphandlers.py
Products/rendezvous/testing.py
Products/rendezvous/browser/RDV_RendezVousEdit.py
Products/rendezvous/browser/RDV_RendezVousUtility.py
Products/rendezvous/browser/RDV_RendezVousView.py
Products/rendezvous/browser/__init__.py
Products/rendezvous/browser/browser.zcml
Products/rendezvous/browser/rendezvous.css
Products/rendezvous/browser/rendezvous.js
Products/rendezvous/browser/templates/RDV_RendezVousEdit.pt
Products/rendezvous/browser/templates/RDV_RendezVousView.pt
Products/rendezvous/browser/templates/calendar.pt
Products/rendezvous/content/RDV_Proposition.py
Products/rendezvous/content/RDV_RendezVous.py
Products/rendezvous/content/__init__.py
Products/rendezvous/content/interfaces.py
Products/rendezvous/i18n/generated.pot
Products/rendezvous/i18n/rendezvous-plone-fr.po
Products/rendezvous/locales/generate.sh
Products/rendezvous/locales/plone.pot
Products/rendezvous/locales/rendezvous.pot
Products/rendezvous/locales/update.sh
Products/rendezvous/locales/en/LC_MESSAGES/plone.po
Products/rendezvous/locales/en/LC_MESSAGES/rendezvous.po
Products/rendezvous/locales/fr/LC_MESSAGES/plone.po
Products/rendezvous/locales/fr/LC_MESSAGES/rendezvous.po
Products/rendezvous/migrations/__init__.py
Products/rendezvous/migrations/configure.zcml
Products/rendezvous/migrations/migrations.py
Products/rendezvous/migrations/migrations.zcml
Products/rendezvous/migrations/profiles/v120/jsregistry.xml
Products/rendezvous/migrations/profiles/v120/metadata.xml
Products/rendezvous/migrations/profiles/v120/types.xml
Products/rendezvous/migrations/profiles/v120/types/RDV_RendezVous.xml
Products/rendezvous/profiles/default/cssregistry.xml
Products/rendezvous/profiles/default/factorytool.xml
Products/rendezvous/profiles/default/import_steps.xml
