Metadata-Version: 1.1
Name: Products.rendezvous
Version: 1.4.2
Summary: A timeboard to select a rendez-vous for Plone. By Ecreall.
Home-page: http://pypi.python.org/pypi/Products.rendezvous
Author: Vincent Fretin and Michael Launay
Author-email: development@ecreall.com
License: GPL
Platform: UNKNOWN
Classifier: Programming Language :: Python
Classifier: License :: OSI Approved :: GNU General Public License (GPL)
Classifier: Operating System :: OS Independent
Classifier: Topic :: Software Development :: User Interfaces
Classifier: Framework :: Plone
